schema_scribe/app.py
schema_scribe/main.py
schema_scribe/prompts.py
schema_scribe/components/db_connectors/__init__.py
schema_scribe/components/db_connectors/duckdb_connector.py
schema_scribe/components/db_connectors/mariadb_connector.py
schema_scribe/components/db_connectors/postgres_connector.py
schema_scribe/components/db_connectors/snowflake_connector.py
schema_scribe/components/db_connectors/sql_base_connector.py
schema_scribe/components/db_connectors/sqlite_connector.py
schema_scribe/components/llm_clients/__init__.py
schema_scribe/components/llm_clients/google_client.py
schema_scribe/components/llm_clients/ollama_client.py
schema_scribe/components/llm_clients/openai_client.py
schema_scribe/components/writers/__init__.py
schema_scribe/components/writers/confluence_writer.py
schema_scribe/components/writers/dbt_markdown_writer.py
schema_scribe/components/writers/dbt_yaml_writer.py
schema_scribe/components/writers/json_writer.py
schema_scribe/components/writers/markdown_writer.py
schema_scribe/components/writers/mermaid_writer.py
schema_scribe/components/writers/notion_writer.py
schema_scribe/components/writers/postgres_comment_writer.py
schema_scribe/core/catalog_generator.py
schema_scribe/core/db_workflow.py
schema_scribe/core/dbt_catalog_generator.py
schema_scribe/core/dbt_parser.py
schema_scribe/core/dbt_workflow.py
schema_scribe/core/exceptions.py
schema_scribe/core/factory.py
schema_scribe/core/interfaces.py
schema_scribe/core/lineage_workflow.py
schema_scribe/core/workflow_helpers.py
schema_scribe/server/main.py
schema_scribe/tests/conftest.py
schema_scribe/tests/integration/test_db_workflow.py
schema_scribe/tests/integration/test_dbt_workflow.py
schema_scribe/tests/integration/test_lineage_workflow.py
schema_scribe/tests/unit/test_dbt.py
schema_scribe/tests/unit/test_factory.py
schema_scribe/tests/unit/test_utils.py
schema_scribe/tests/unit/db_connectors/test_duckdb_connector.py
schema_scribe/tests/unit/db_connectors/test_mariadb_connector.py
schema_scribe-0.2.0.dist-info/METADATA
schema_scribe-0.2.0.dist-info/WHEEL
schema_scribe-0.2.0.dist-info/entry_points.txt
schema_scribe-0.2.0.dist-info/top_level.txt
schema_scribe-0.2.0.dist-info/RECORD
