Metadata-Version: 2.4
Name: schema-scribe
Version: 0.2.0
Summary: AI-powered data documentation generator for databases and dbt projects.
Author-email: DongWon Moon <ansehddnjs187@gmail.com>
Classifier: Programming Language :: Python :: 3
Classifier: Programming Language :: Python :: 3.10
Classifier: Programming Language :: Python :: 3.11
Classifier: Programming Language :: Python :: 3.12
Classifier: License :: OSI Approved :: MIT License
Classifier: Operating System :: OS Independent
Classifier: Topic :: Database
Classifier: Topic :: Scientific/Engineering :: Artificial Intelligence
Classifier: Topic :: Software Development :: Documentation
Requires-Python: >=3.10
Requires-Dist: typer>=0.9.0
Requires-Dist: openai>=1.0.0
Requires-Dist: python-dotenv>=1.0.0
Requires-Dist: PyYAML>=6.0
Requires-Dist: ruamel.yaml>=0.17.0
Provides-Extra: postgres
Requires-Dist: psycopg2-binary>=2.9.0; extra == "postgres"
Provides-Extra: mariadb
Requires-Dist: mysql-connector-python>=8.0.0; extra == "mariadb"
Provides-Extra: google
Requires-Dist: google-generativeai>=0.4.0; extra == "google"
Provides-Extra: ollama
Requires-Dist: ollama>=0.1.0; extra == "ollama"
Provides-Extra: confluence
Requires-Dist: atlassian-python-api>=3.40.0; extra == "confluence"
Provides-Extra: snowflake
Requires-Dist: snowflake-connector-python>=3.0.0; extra == "snowflake"
Provides-Extra: notion
Requires-Dist: notion-client>=2.0.0; extra == "notion"
Provides-Extra: server
Requires-Dist: fastapi>=0.100.0; extra == "server"
Requires-Dist: uvicorn[standard]>=0.20.0; extra == "server"
Provides-Extra: test
Requires-Dist: pytest>=7.0.0; extra == "test"
Requires-Dist: pytest-mock>=3.0.0; extra == "test"
Requires-Dist: dbt-core>=1.7.0; extra == "test"
Requires-Dist: dbt-duckdb>=1.7.0; extra == "test"
Provides-Extra: all
Requires-Dist: psycopg2-binary>=2.9.0; extra == "all"
Requires-Dist: mysql-connector-python>=8.0.0; extra == "all"
Requires-Dist: google-generativeai>=0.4.0; extra == "all"
Requires-Dist: ollama>=0.1.0; extra == "all"
Requires-Dist: atlassian-python-api>=3.40.0; extra == "all"
Requires-Dist: snowflake-connector-python>=3.0.0; extra == "all"
Requires-Dist: notion-client>=2.0.0; extra == "all"
Requires-Dist: pytest>=7.0.0; extra == "all"
Requires-Dist: pytest-mock>=3.0.0; extra == "all"
Requires-Dist: dbt-core>=1.7.0; extra == "all"
Requires-Dist: dbt-duckdb>=1.7.0; extra == "all"
Requires-Dist: fastapi>=0.100.0; extra == "all"
Requires-Dist: uvicorn[standard]>=0.20.0; extra == "all"
